django_easyfilters/filterset.py
django_easyfilters/utils.py
django_easyfilters/queries.py
django_easyfilters/filters.py
django_easyfilters/models.py
django_easyfilters/ranges.py
django_easyfilters/__init__.py
django_easyfilters/templates/django-easyfilters/default.html
django_easyfilters/tests/test_ranges.py
django_easyfilters/tests/test_filterset.py
django_easyfilters/tests/admin.py
django_easyfilters/tests/views.py
django_easyfilters/tests/models.py
django_easyfilters/tests/__init__.py
django_easyfilters/tests/urls.py
django_easyfilters/tests/templates/authors.html
django_easyfilters/tests/templates/template_for_tests.html
django_easyfilters/tests/templates/book_search.html
django_easyfilters/tests/templates/base.html
django_easyfilters/tests/templates/books.html
django_easyfilters/tests/fixtures/django_easyfilters_tests.json
django_easyfilters-0.6.dist-info/RECORD
django_easyfilters-0.6.dist-info/DESCRIPTION.rst
django_easyfilters-0.6.dist-info/METADATA
django_easyfilters-0.6.dist-info/top_level.txt
django_easyfilters-0.6.dist-info/metadata.json
django_easyfilters-0.6.dist-info/WHEEL
