Metadata-Version: 2.0
Name: django-easyfilters
Version: 0.6
Summary: Easy creation of link-based filtering for a list of Django model objects.
Home-page: https://bitbucket.org/spookylukey/django-easyfilters/
Author: Luke Plant
Author-email: L.Plant.98@cantab.net
License: MIT
Keywords: django filter autofilter drilldown easy simple
Platform: UNKNOWN
Classifier: Development Status :: 5 - Production/Stable
Classifier: Environment :: Web Environment
Classifier: Intended Audience :: Developers
Classifier: License :: OSI Approved :: MIT License
Classifier: Operating System :: OS Independent
Classifier: Programming Language :: Python :: 2.6
Classifier: Programming Language :: Python :: 2.7
Classifier: Programming Language :: Python :: 3.3
Classifier: Programming Language :: Python :: 3.4
Classifier: Framework :: Django
Classifier: Topic :: Software Development :: User Interfaces
Requires-Dist: django (>=1.3)
Requires-Dist: python-dateutil
Requires-Dist: six
